[
{"name": "Birddog", "intr": "30", "reps": "6 each"},

{"name": "Plank to Pushup", "intr": "40", "reps": "20"},

{"name": "Birddog", "intr": "30", "reps": "6 each"},

{"name": "Plank to Pushup", "intr": "40", "reps": "20"},

{"name": "Birddog", "intr": "30", "reps": "6 each"},

{"name": "Plank to Pushup", "intr": "40", "reps": "20"},

{"name": "Deadbug", "intr": "30", "reps": "8 each"},

{"name": "One-Legged Glute Bridge  (SLOW!)", "intr": "45", "reps": "10 each"},

{"name": "Deadbug", "intr": "30", "reps": "8 each"},

{"name": "One-Legged Glute Bridge  (SLOW!)", "intr": "45", "reps": "10 each"},

{"name": "Deadbug", "intr": "30", "reps": "8 each"},

{"name": "One-Legged Glute Bridge  (SLOW!)", "intr": "45", "reps": "10 each"},

{"name": "Reverse Lunges", "intr": "45", "reps": "10 each"},

{"name": "Rest", "intr": "15", "reps": ":15"},

{"name": "T Push Ups", "intr": "30", "reps": "10"},

{"name": "Rest", "intr": "15", "reps": ":15"},

{"name": "Reverse Lunges", "intr": "45", "reps": "10 each"},

{"name": "Rest", "intr": "15", "reps": ":15"},

{"name": "T Push Ups", "intr": "30", "reps": "10"},

{"name": "Rest", "intr": "15", "reps": ":15"},

{"name": "Reverse Lunges", "intr": "45", "reps": "10 each"},

{"name": "Rest", "intr": "15", "reps": ":15"},

{"name": "T Push Ups", "intr": "30", "reps": "10"},

{"name": "Rest", "intr": "15", "reps": ":15"},

{"name": "Reverse Lunges", "intr": "45", "reps": "10 each"},

{"name": "Rest", "intr": "15", "reps": ":15"},

{"name": "T Push Ups", "intr": "30", "reps": "10"},

{"name": "Rest", "intr": "15", "reps": ":15"},

{"name": "Steam Engines", "intr": "30", "reps": "20"},

{"name": "Rest", "intr": "10", "reps": ":10"},

{"name": "Star Plank", "intr": "30", "reps": ":30"},

{"name": "Rest", "intr": "10", "reps": ":10"},

{"name": "Steam Engines", "intr": "30", "reps": "20"},

{"name": "Rest", "intr": "10", "reps": ":10"},

{"name": "Star Plank", "intr": "30", "reps": ":30"},

{"name": "Rest", "intr": "10", "reps": ":10"},

{"name": "Steam Engines", "intr": "30", "reps": "20"},

{"name": "Rest", "intr": "10", "reps": ":10"},

{"name": "Star Plank", "intr": "30", "reps": ":30"},

{"name": "Rest", "intr": "10", "reps": ":10"},

{"name": "Steam Engines", "intr": "30", "reps": "20"},

{"name": "Rest", "intr": "10", "reps": ":10"},

{"name": "Star Plank", "intr": "30", "reps": ":30"},

{"name": "Rest", "intr": "10", "reps": ":10"},

{"name": "Bulgarian Split Squat", "intr": "60", "reps": "10"},

{"name": "Rest", "intr": "30", "reps": ":10"},

{"name": "Kneeling Step Up", "intr": "45", "reps": "8 each"},

{"name": "Rest", "intr": "15", "reps": ":15"},

{"name": "Tuck Jump (Knees to Chest)", "intr": "30", "reps": "6"},

{"name": "Bulgarian Split Squat", "intr": "60", "reps": "10"},

{"name": "Rest", "intr": "30", "reps": ":10"},

{"name": "Kneeling Step Up", "intr": "45", "reps": "8 each"},

{"name": "Rest", "intr": "15", "reps": ":15"},

{"name": "Tuck Jump (Knees to Chest)", "intr": "30", "reps": "6"},

{"name": "Bulgarian Split Squat", "intr": "60", "reps": "10"},

{"name": "Rest", "intr": "30", "reps": ":10"},

{"name": "Kneeling Step Up", "intr": "45", "reps": "8 each"},

{"name": "Rest", "intr": "15", "reps": ":15"},

{"name": "Tuck Jump (Knees to Chest)", "intr": "30", "reps": "6"},

{"name": "Rest (David is so cool!)", "intr": "60", "reps": ":60"},

{"name": "Plank Marches", "intr": "45", "reps": "20 each"},

{"name": "Elbow to Knees", "intr": "45", "reps": "20 each"},

{"name": "Plank Marches", "intr": "45", "reps": "20 each"},

{"name": "Elbow to Knees", "intr": "45", "reps": "20 each"},

{"name": "Rest", "intr": "30", "reps": ":30"},

{"name": "Hollow Rock", "intr": "30", "reps": ":30"},

{"name": "Oblique Leg Raises", "intr": "60", "reps": "40 alternating"},

{"name": "Hollow Rock", "intr": "30", "reps": ":30"},

{"name": "Oblique Leg Raises", "intr": "60", "reps": "40 alternating"},

{"name": "Hollow Rock", "intr": "30", "reps": ":30"},

{"name": "Oblique Leg Raises", "intr": "60", "reps": "40 alternating"},

{"name": "Rest", "intr": "30", "reps": ":30"},

{"name": "Reverse Crunches", "intr": "60", "reps": "50"},

{"name": "Flutter Kicks", "intr": "60", "reps": "60"},

{"name": "Side Plank Raises (LEFT)", "intr": "30", "reps": "12"},

{"name": "Side Plank Raises (RIGHT)", "intr": "30", "reps": "12"},

{"name": "Rest (STRETCH TIME !) ", "intr": "30", "reps": ":30"},

{"name": "Seal", "intr": "60", "reps": ":60"},

{"name": "Downward Dog", "intr": "60", "reps": ":60"},

{"name": "Childs Pose", "intr": "60", "reps": ":60"},

{"name": "Pigeon", "intr": "60", "reps": ":60"},

{"name": "Seated Legs Apart Reach", "intr": "45", "reps": ":45"},

{"name": "Supine Spinal Twist (LEFT)", "intr": "30", "reps": ":30"},

{"name": "Supine Spinal Twist (RIGHT)", "intr": "30", "reps": ":30"}
]
